mvdtool.cpython-311-x86_64-linux-gnu.so
MVDTool.libs/libhdf5-7f3c9bd7.so.200.1.0
MVDTool.libs/libaec-8db54129.so.0.0.10
MVDTool.libs/libsz-60c3b967.so.2.0.1
MVDTool-2.4.11.dist-info/top_level.txt
MVDTool-2.4.11.dist-info/AUTHORS.txt
MVDTool-2.4.11.dist-info/METADATA
MVDTool-2.4.11.dist-info/LICENSE
MVDTool-2.4.11.dist-info/RECORD
MVDTool-2.4.11.dist-info/WHEEL
