Metadata-Version: 2.1
Name: MVDTool
Version: 2.4.11
Summary: Python bindings to the MVD3 neuroscience file format
Home-page: https://github.com/BlueBrain/MVDTool
Author: Blue Brain Project, EPFL
Author-email: bbp-ou-hpc@groupes.epfl.ch
License-File: LICENSE
License-File: AUTHORS.txt
Requires-Dist: numpy
